docs/docs/CHANGELOG.md
sktransf/__init__.py
sktransf/cleaner/__init__.py
sktransf/cleaner/base.py
sktransf/scaler/__init__.py
sktransf/scaler/standard.py
sktransf/selector/__init__.py
sktransf/selector/sku.py
sktransf/selector/unique.py
sktransf/transformer/__init__.py
sktransf/transformer/bool.py
sktransf/transformer/log.py
sktransf/utils/__init__.py
sktransf/utils/get_titanic.py
sktransf/utils/use_case.py
sktransf/validators.py
scikit_transformers-0.3.2.dist-info/LICENSE
scikit_transformers-0.3.2.dist-info/METADATA
scikit_transformers-0.3.2.dist-info/WHEEL
scikit_transformers-0.3.2.dist-info/RECORD
