Metadata-Version: 2.1
Name: scikit-transformers
Version: 0.3.2
Summary: scikit-transformers is a very usefull package to enable and provide custom transformers such as LogColumnTransformer, BoolColumnTransformers and others fancy transformers.
Home-page: https://alexandregazagnes.github.io/scikit-transformers/
License: GPL-3.0
Keywords: python,machine learning,sklearn,transformers,scikit-learn,tools,data,pandas
Author: AlexandreGazagnes
Author-email: alex@gazagnes.net
Maintainer: AlexandreGazagnes
Maintainer-email: alex@gazagnes.net
Requires-Python: >=3.9,<4
Classifier: Development Status :: 5 - Production/Stable
Classifier: Environment :: Other Environment
Classifier: Intended Audience :: Developers
Classifier: Intended Audience :: Education
Classifier: Intended Audience :: Information Technology
Classifier: License :: OSI Approved :: GNU General Public License v3 (GPLv3)
Classifier: Programming Language :: Python
Classifier: Programming Language :: Python :: 3
Classifier: Programming Language :: Python :: 3.9
Classifier: Programming Language :: Python :: 3.10
Classifier: Programming Language :: Python :: 3.11
Classifier: Programming Language :: Python :: 3.12
Classifier: Programming Language :: Python :: 3 :: Only
Classifier: Topic :: Scientific/Engineering :: Artificial Intelligence
Classifier: Topic :: Scientific/Engineering :: Information Analysis
Classifier: Topic :: Software Development :: Libraries :: Python Modules
Requires-Dist: pandas (>=1.4.0)
Requires-Dist: scikit-learn (>=1.0.0)
Project-URL: Changelog, https://alexandregazagnes.github.io/scikit-transformers/CHANGELOG/
Project-URL: Documentation, https://alexandregazagnes.github.io/scikit-transformers/
Project-URL: Issues, https://github.com/AlexandreGazagnes/scikit-transformers/issues
Project-URL: Repository, https://github.com/AlexandreGazagnes/scikit-transformers/tree/main
